README.md
setup.py
pycartool/__init__.py
pycartool/__main__.py
pycartool/regions_of_interest.py
pycartool/source_estimate.py
pycartool/source_space.py
pycartool.egg-info/PKG-INFO
pycartool.egg-info/SOURCES.txt
pycartool.egg-info/dependency_links.txt
pycartool.egg-info/requires.txt
pycartool.egg-info/top_level.txt
pycartool/io/__init__.py
pycartool/io/inverse_solution.py
pycartool/io/leadfield.py
pycartool/io/montage.py
pycartool/io/sef.py
pycartool/tests/__init__.py
pycartool/tests/test_montage.py
pycartool/tests/test_regions_of_interest.py
pycartool/tests/test_sef.py
pycartool/tests/test_source_estimate.py
pycartool/tests/test_source_space.py
pycartool/utils/__init__.py