Metadata-Version: 2.1
Name: pycartool
Version: 0.1.1
Summary: A simple open source Python package for I/O between Cartool and MNE ( and more generally python)
Home-page: https://github.com/Functional-Brain-Mapping-Laboratory/PyCartool
Author: Victor Férat
Author-email: victor.ferat@live.fr
License: BSD-3-Clause
Platform: UNKNOWN
Classifier: Development Status :: 3 - Alpha
Classifier: Intended Audience :: Science/Research
Classifier: Topic :: Scientific/Engineering
Classifier: License :: OSI Approved :: BSD License
Classifier: Programming Language :: Python :: 3.6
Classifier: Programming Language :: Python :: 3.7
Requires-Python: >=3.6
